{"cameraMode":{"drawMode":0,"name":"Shaded","section":"Shading Mode"},"sceneLighting":true,"audioPlay":false,"sceneViewState":{"m_AlwaysRefresh":false,"showFog":true,"showSkybox":true,"showFlares":true,"showImageEffects":true,"showParticleSystems":true,"showVisualEffectGraphs":true,"m_FxEnabled":true},"in2DMode":false,"pivot":{"x":3.6389007568359377,"y":-69.88358306884766,"z":-127.33863067626953},"rotation":{"x":0.027932913973927499,"y":-0.9648557305335999,"z":0.23491297662258149,"w":0.11518162488937378},"size":122.02446746826172,"orthographic":false}